{
  "success": true,
  "message": "OK",
  "data": {
    "playerId": "289167",
    "history": {
      "terminated": [
        {
          "id": "5934954",
          "transferSource": {
            "competitionId": "",
            "countryId": 0,
            "clubId": "515",
            "coachId": "0"
          },
          "transferDestination": {
            "competitionId": "PL1",
            "countryId": 135,
            "clubId": "2300",
            "coachId": "40054"
          },
          "details": {
            "playerId": "289167",
            "date": "2025-09-11T00:00:00+02:00",
            "contractUntilDate": "2027-06-30T00:00:00+02:00",
            "seasonId": 2025,
            "isPending": false,
            "marketValue": {
              "value": 1200000,
              "currency": "EUR",
              "compact": {
                "prefix": "€",
                "content": "1.20",
                "suffix": "M"
              }
            },
            "age": 27,
            "fee": {
              "value": null,
              "currency": "",
              "compact": {
                "prefix": "",
                "content": "-",
                "suffix": ""
              }
            },
            "season": {
              "id": 2025,
              "display": "25/26",
              "cyclicalName": "2026",
              "nonCyclicalName": "25/26"
            }
          },
          "typeDetails": {
            "type": "STANDARD",
            "name": "",
            "feeDescription": ""
          },
          "relativeUrl": "/kamil-jozwiak/transfers/spieler/289167/transfer_id/5934954"
        },
        {
          "id": "5693011",
          "transferSource": {
            "competitionId": "ES2",
            "countryId": 157,
            "clubId": "16795",
            "coachId": "19446"
          },
          "transferDestination": {
            "competitionId": "",
            "countryId": 0,
            "clubId": "515",
            "coachId": "0"
          },
          "details": {
            "playerId": "289167",
            "date": "2025-07-01T00:00:00+02:00",
            "contractUntilDate": null,
            "seasonId": 2025,
            "isPending": false,
            "marketValue": {
              "value": 1200000,
              "currency": "EUR",
              "compact": {
                "prefix": "€",
                "content": "1.20",
                "suffix": "M"
              }
            },
            "age": 27,
            "fee": {
              "value": null,
              "currency": "",
              "compact": {
                "prefix": "",
                "content": "-",
                "suffix": ""
              }
            },
            "season": {
              "id": 2025,
              "display": "25/26",
              "cyclicalName": "2026",
              "nonCyclicalName": "25/26"
            }
          },
          "typeDetails": {
            "type": "STANDARD",
            "name": "",
            "feeDescription": ""
          },
          "relativeUrl": "/kamil-jozwiak/transfers/spieler/289167/transfer_id/5693011"
        },
        {
          "id": "4864579",
          "transferSource": {
            "competitionId": "MLS1",
            "countryId": 184,
            "clubId": "78435",
            "coachId": "15315"
          },
          "transferDestination": {
            "competitionId": "ES1",
            "countryId": 157,
            "clubId": "16795",
            "coachId": "47797"
          },
          "details": {
            "playerId": "289167",
            "date": "2024-02-01T00:00:00+01:00",
            "contractUntilDate": "2025-06-30T00:00:00+02:00",
            "seasonId": 2023,
            "isPending": false,
            "marketValue": {
              "value": 2500000,
              "currency": "EUR",
              "compact": {
                "prefix": "€",
                "content": "2.50",
                "suffix": "M"
              }
            },
            "age": 25,
            "fee": {
              "value": 250000,
              "currency": "EUR",
              "compact": {
                "prefix": "€",
                "content": "250.00",
                "suffix": "K"
              }
            },
            "remainingContractPeriod": {
              "days": 515,
              "daysDisplay": "1 Year, 4 Months, 29 Days"
            },
            "season": {
              "id": 2023,
              "display": "23/24",
              "cyclicalName": "2024",
              "nonCyclicalName": "23/24"
            }
          },
          "typeDetails": {
            "type": "STANDARD",
            "name": "",
            "feeDescription": ""
          },
          "relativeUrl": "/kamil-jozwiak/transfers/spieler/289167/transfer_id/4864579"
        },
        {
          "id": "3779145",
          "transferSource": {
            "competitionId": "GB2",
            "countryId": 189,
            "clubId": "22",
            "coachId": "86680"
          },
          "transferDestination": {
            "competitionId": "MLS1",
            "countryId": 184,
            "clubId": "78435",
            "coachId": "69675"
          },
          "details": {
            "playerId": "289167",
            "date": "2022-03-11T00:00:00+01:00",
            "contractUntilDate": "2025-06-30T00:00:00+02:00",
            "seasonId": 2021,
            "isPending": false,
            "marketValue": {
              "value": 3500000,
              "currency": "EUR",
              "compact": {
                "prefix": "€",
                "content": "3.50",
                "suffix": "M"
              }
            },
            "age": 23,
            "fee": {
              "value": 2363636,
              "currency": "EUR",
              "compact": {
                "prefix": "€",
                "content": "2.36",
                "suffix": "M"
              }
            },
            "remainingContractPeriod": {
              "days": 842,
              "daysDisplay": "2 Years, 3 Months, 19 Days"
            },
            "season": {
              "id": 2021,
              "display": "21/22",
              "cyclicalName": "2022",
              "nonCyclicalName": "21/22"
            }
          },
          "typeDetails": {
            "type": "STANDARD",
            "name": "",
            "feeDescription": ""
          },
          "relativeUrl": "/kamil-jozwiak/transfers/spieler/289167/transfer_id/3779145"
        },
        {
          "id": "3062807",
          "transferSource": {
            "competitionId": "PL1",
            "countryId": 135,
            "clubId": "238",
            "coachId": "25215"
          },
          "transferDestination": {
            "competitionId": "GB2",
            "countryId": 189,
            "clubId": "22",
            "coachId": "6405"
          },
          "details": {
            "playerId": "289167",
            "date": "2020-09-16T00:00:00+02:00",
            "contractUntilDate": "2024-06-30T00:00:00+02:00",
            "seasonId": 2020,
            "isPending": false,
            "marketValue": {
              "value": 4000000,
              "currency": "EUR",
              "compact": {
                "prefix": "€",
                "content": "4.00",
                "suffix": "M"
              }
            },
            "age": 22,
            "fee": {
              "value": 4300000,
              "currency": "EUR",
              "compact": {
                "prefix": "€",
                "content": "4.30",
                "suffix": "M"
              }
            },
            "remainingContractPeriod": {
              "days": 652,
              "daysDisplay": "1 Year, 9 Months, 14 Days"
            },
            "season": {
              "id": 2020,
              "display": "20/21",
              "cyclicalName": "2021",
              "nonCyclicalName": "20/21"
            }
          },
          "typeDetails": {
            "type": "STANDARD",
            "name": "",
            "feeDescription": ""
          },
          "relativeUrl": "/kamil-jozwiak/transfers/spieler/289167/transfer_id/3062807"
        },
        {
          "id": "1664387",
          "transferSource": {
            "competitionId": "PL2",
            "countryId": 135,
            "clubId": "6456",
            "coachId": "11104"
          },
          "transferDestination": {
            "competitionId": "PL1",
            "countryId": 135,
            "clubId": "238",
            "coachId": "5197"
          },
          "details": {
            "playerId": "289167",
            "date": "2017-06-30T00:00:00+02:00",
            "contractUntilDate": "2022-06-30T00:00:00+02:00",
            "seasonId": 2016,
            "isPending": false,
            "marketValue": {
              "value": 200000,
              "currency": "EUR",
              "compact": {
                "prefix": "€",
                "content": "200.00",
                "suffix": "K"
              }
            },
            "age": 19,
            "remainingContractPeriod": {
              "days": 0,
              "daysDisplay": "Unknown"
            },
            "season": {
              "id": 2016,
              "display": "16/17",
              "cyclicalName": "2017",
              "nonCyclicalName": "16/17"
            }
          },
          "typeDetails": {
            "type": "RETURNED_FROM_PREVIOUS_LOAN",
            "name": "End of loan",
            "feeDescription": "End of loan"
          },
          "relativeUrl": "/kamil-jozwiak/transfers/spieler/289167/transfer_id/1664387"
        },
        {
          "id": "1664386",
          "transferSource": {
            "competitionId": "PL1",
            "countryId": 135,
            "clubId": "238",
            "coachId": "5197"
          },
          "transferDestination": {
            "competitionId": "PL2",
            "countryId": 135,
            "clubId": "6456",
            "coachId": "12950"
          },
          "details": {
            "playerId": "289167",
            "date": "2017-01-05T00:00:00+01:00",
            "contractUntilDate": "2017-06-30T00:00:00+02:00",
            "seasonId": 2016,
            "isPending": false,
            "marketValue": {
              "value": 250000,
              "currency": "EUR",
              "compact": {
                "prefix": "€",
                "content": "250.00",
                "suffix": "K"
              }
            },
            "age": 18,
            "remainingContractPeriod": {
              "days": 906,
              "daysDisplay": "2 Years, 5 Months, 25 Days"
            },
            "season": {
              "id": 2016,
              "display": "16/17",
              "cyclicalName": "2017",
              "nonCyclicalName": "16/17"
            }
          },
          "typeDetails": {
            "type": "ACTIVE_LOAN_TRANSFER",
            "name": "loan transfer",
            "feeDescription": "loan transfer"
          },
          "relativeUrl": "/kamil-jozwiak/transfers/spieler/289167/transfer_id/1664386"
        },
        {
          "id": "1432036",
          "transferSource": {
            "competitionId": "",
            "countryId": 135,
            "clubId": "8468",
            "coachId": "31677"
          },
          "transferDestination": {
            "competitionId": "PL1",
            "countryId": 135,
            "clubId": "238",
            "coachId": "4586"
          },
          "details": {
            "playerId": "289167",
            "date": "2016-01-14T00:00:00+01:00",
            "contractUntilDate": "2019-06-30T00:00:00+02:00",
            "seasonId": 2015,
            "isPending": false,
            "marketValue": {
              "value": 150000,
              "currency": "EUR",
              "compact": {
                "prefix": "€",
                "content": "150.00",
                "suffix": "K"
              }
            },
            "age": 17,
            "fee": {
              "value": null,
              "currency": "",
              "compact": {
                "prefix": "",
                "content": "-",
                "suffix": ""
              }
            },
            "season": {
              "id": 2015,
              "display": "15/16",
              "cyclicalName": "2016",
              "nonCyclicalName": "15/16"
            }
          },
          "typeDetails": {
            "type": "STANDARD",
            "name": "",
            "feeDescription": ""
          },
          "relativeUrl": "/kamil-jozwiak/transfers/spieler/289167/transfer_id/1432036"
        },
        {
          "id": "1218455",
          "transferSource": {
            "competitionId": "PLJF",
            "countryId": 135,
            "clubId": "15519",
            "coachId": "31677"
          },
          "transferDestination": {
            "competitionId": "",
            "countryId": 135,
            "clubId": "8468",
            "coachId": "28579"
          },
          "details": {
            "playerId": "289167",
            "date": "2014-07-01T00:00:00+02:00",
            "contractUntilDate": null,
            "seasonId": 2014,
            "isPending": false,
            "marketValue": {
              "value": 0,
              "currency": "EUR",
              "compact": {
                "prefix": "€",
                "content": "0.00",
                "suffix": ""
              }
            },
            "age": 16,
            "fee": {
              "value": null,
              "currency": "",
              "compact": {
                "prefix": "",
                "content": "-",
                "suffix": ""
              }
            },
            "season": {
              "id": 2014,
              "display": "14/15",
              "cyclicalName": "2015",
              "nonCyclicalName": "14/15"
            }
          },
          "typeDetails": {
            "type": "STANDARD",
            "name": "",
            "feeDescription": ""
          },
          "relativeUrl": "/kamil-jozwiak/transfers/spieler/289167/transfer_id/1218455"
        },
        {
          "id": "1267079",
          "transferSource": {
            "competitionId": "",
            "countryId": 135,
            "clubId": "42552",
            "coachId": "0"
          },
          "transferDestination": {
            "competitionId": "",
            "countryId": 135,
            "clubId": "15519",
            "coachId": "27188"
          },
          "details": {
            "playerId": "289167",
            "date": "2011-07-01T00:00:00+02:00",
            "contractUntilDate": null,
            "seasonId": 2011,
            "isPending": false,
            "marketValue": {
              "value": 0,
              "currency": "EUR",
              "compact": {
                "prefix": "€",
                "content": "0.00",
                "suffix": ""
              }
            },
            "age": 13,
            "fee": {
              "value": null,
              "currency": "",
              "compact": {
                "prefix": "",
                "content": "Free Transfer",
                "suffix": ""
              }
            },
            "season": {
              "id": 2011,
              "display": "11/12",
              "cyclicalName": "2012",
              "nonCyclicalName": "11/12"
            }
          },
          "typeDetails": {
            "type": "STANDARD",
            "name": "",
            "feeDescription": ""
          },
          "relativeUrl": "/kamil-jozwiak/transfers/spieler/289167/transfer_id/1267079"
        }
      ],
      "pending": [],
      "url": "",
      "feeSum": {
        "value": 6913636,
        "currency": "EUR",
        "compact": {
          "prefix": "€",
          "content": "6.91",
          "suffix": "M"
        }
      },
      "averageAge": 28,
      "totalMarketValue": {
        "value": 600000,
        "currency": "EUR",
        "compact": {
          "prefix": "€",
          "content": "600.00",
          "suffix": "K"
        }
      }
    },
    "clubIds": [
      "515",
      "2300",
      "16795",
      "78435",
      "22",
      "238",
      "6456",
      "8468",
      "15519",
      "42552"
    ],
    "coachIds": [
      "40054",
      "19446",
      "15315",
      "47797",
      "86680",
      "69675",
      "25215",
      "6405",
      "11104",
      "5197",
      "12950",
      "31677",
      "4586",
      "28579",
      "27188"
    ],
    "competitionIds": [
      "PL1",
      "ES2",
      "MLS1",
      "ES1",
      "GB2",
      "PL2",
      "PLJF"
    ],
    "mostRecentTransfer": {
      "id": "5934954",
      "transferSource": {
        "competitionId": "",
        "countryId": 0,
        "clubId": "515",
        "coachId": "0"
      },
      "transferDestination": {
        "competitionId": "PL1",
        "countryId": 135,
        "clubId": "2300",
        "coachId": "40054"
      },
      "details": {
        "playerId": "289167",
        "date": "2025-09-11T00:00:00+02:00",
        "contractUntilDate": "2027-06-30T00:00:00+02:00",
        "seasonId": 2025,
        "isPending": false,
        "marketValue": {
          "value": 1200000,
          "currency": "EUR",
          "compact": {
            "prefix": "€",
            "content": "1.20",
            "suffix": "M"
          }
        },
        "age": 27,
        "fee": {
          "value": null,
          "currency": "",
          "compact": {
            "prefix": "",
            "content": "-",
            "suffix": ""
          }
        },
        "season": {
          "id": 2025,
          "display": "25/26",
          "cyclicalName": "2026",
          "nonCyclicalName": "25/26"
        }
      },
      "typeDetails": {
        "type": "STANDARD",
        "name": "",
        "feeDescription": ""
      },
      "relativeUrl": "/kamil-jozwiak/transfers/spieler/289167/transfer_id/5934954"
    }
  }
}