{
  "success": true,
  "message": "OK",
  "data": {
    "playerId": "649020",
    "history": {
      "terminated": [
        {
          "id": "5807621",
          "transferSource": {
            "competitionId": "GB1",
            "countryId": 189,
            "clubId": "543",
            "coachId": "7571"
          },
          "transferDestination": {
            "competitionId": "FR1",
            "countryId": 50,
            "clubId": "347",
            "coachId": "7218"
          },
          "details": {
            "playerId": "649020",
            "date": "2025-07-24T00:00:00+02:00",
            "contractUntilDate": "2026-06-30T00:00:00+02:00",
            "seasonId": 2025,
            "isPending": false,
            "marketValue": {
              "value": 5000000,
              "currency": "EUR",
              "compact": {
                "prefix": "€",
                "content": "5.00",
                "suffix": "M"
              }
            },
            "age": 23,
            "remainingContractPeriod": {
              "days": 706,
              "daysDisplay": "1 Year, 11 Months, 6 Days"
            },
            "season": {
              "id": 2025,
              "display": "25/26",
              "cyclicalName": "2026",
              "nonCyclicalName": "25/26"
            }
          },
          "typeDetails": {
            "type": "ACTIVE_LOAN_TRANSFER",
            "name": "loan transfer",
            "feeDescription": "loan transfer"
          },
          "relativeUrl": "/boubacar-traore/transfers/spieler/649020/transfer_id/5807621"
        },
        {
          "id": "4178193",
          "transferSource": {
            "competitionId": "FR1",
            "countryId": 50,
            "clubId": "347",
            "coachId": "1227"
          },
          "transferDestination": {
            "competitionId": "GB1",
            "countryId": 189,
            "clubId": "543",
            "coachId": "6615"
          },
          "details": {
            "playerId": "649020",
            "date": "2023-07-01T00:00:00+02:00",
            "contractUntilDate": "2027-06-30T00:00:00+02:00",
            "seasonId": 2023,
            "isPending": false,
            "marketValue": {
              "value": 5000000,
              "currency": "EUR",
              "compact": {
                "prefix": "€",
                "content": "5.00",
                "suffix": "M"
              }
            },
            "age": 21,
            "fee": {
              "value": 11000000,
              "currency": "EUR",
              "compact": {
                "prefix": "€",
                "content": "11.00",
                "suffix": "M"
              }
            },
            "remainingContractPeriod": {
              "days": 365,
              "daysDisplay": "11 Months, 29 Days"
            },
            "season": {
              "id": 2023,
              "display": "23/24",
              "cyclicalName": "2024",
              "nonCyclicalName": "23/24"
            }
          },
          "typeDetails": {
            "type": "STANDARD",
            "name": "",
            "feeDescription": ""
          },
          "relativeUrl": "/boubacar-traore/transfers/spieler/649020/transfer_id/4178193"
        },
        {
          "id": "4052408",
          "transferSource": {
            "competitionId": "GB1",
            "countryId": 189,
            "clubId": "543",
            "coachId": "6615"
          },
          "transferDestination": {
            "competitionId": "FR1",
            "countryId": 50,
            "clubId": "347",
            "coachId": "1227"
          },
          "details": {
            "playerId": "649020",
            "date": "2023-06-30T00:00:00+02:00",
            "contractUntilDate": "2024-06-30T00:00:00+02:00",
            "seasonId": 2022,
            "isPending": false,
            "marketValue": {
              "value": 5000000,
              "currency": "EUR",
              "compact": {
                "prefix": "€",
                "content": "5.00",
                "suffix": "M"
              }
            },
            "age": 21,
            "remainingContractPeriod": {
              "days": 0,
              "daysDisplay": "Unknown"
            },
            "season": {
              "id": 2022,
              "display": "22/23",
              "cyclicalName": "2023",
              "nonCyclicalName": "22/23"
            }
          },
          "typeDetails": {
            "type": "RETURNED_FROM_PREVIOUS_LOAN",
            "name": "End of loan",
            "feeDescription": "End of loan"
          },
          "relativeUrl": "/boubacar-traore/transfers/spieler/649020/transfer_id/4052408"
        },
        {
          "id": "4052407",
          "transferSource": {
            "competitionId": "FR2",
            "countryId": 50,
            "clubId": "347",
            "coachId": "1227"
          },
          "transferDestination": {
            "competitionId": "GB1",
            "countryId": 189,
            "clubId": "543",
            "coachId": "61477"
          },
          "details": {
            "playerId": "649020",
            "date": "2022-09-01T00:00:00+02:00",
            "contractUntilDate": "2023-06-30T00:00:00+02:00",
            "seasonId": 2022,
            "isPending": false,
            "marketValue": {
              "value": 1800000,
              "currency": "EUR",
              "compact": {
                "prefix": "€",
                "content": "1.80",
                "suffix": "M"
              }
            },
            "age": 21,
            "fee": {
              "value": 2000000,
              "currency": "EUR",
              "compact": {
                "prefix": "€",
                "content": "2.00",
                "suffix": "M"
              }
            },
            "remainingContractPeriod": {
              "days": 668,
              "daysDisplay": "1 Year, 9 Months, 29 Days"
            },
            "season": {
              "id": 2022,
              "display": "22/23",
              "cyclicalName": "2023",
              "nonCyclicalName": "22/23"
            }
          },
          "typeDetails": {
            "type": "ACTIVE_LOAN_TRANSFER",
            "name": "loan transfer",
            "feeDescription": "Loan fee"
          },
          "relativeUrl": "/boubacar-traore/transfers/spieler/649020/transfer_id/4052407"
        },
        {
          "id": "2652849",
          "transferSource": {
            "competitionId": "",
            "countryId": 105,
            "clubId": "21375",
            "coachId": "0"
          },
          "transferDestination": {
            "competitionId": "FR1",
            "countryId": 50,
            "clubId": "347",
            "coachId": "27454"
          },
          "details": {
            "playerId": "649020",
            "date": "2019-08-22T00:00:00+02:00",
            "contractUntilDate": "2024-06-30T00:00:00+02:00",
            "seasonId": 2019,
            "isPending": false,
            "marketValue": {
              "value": 100000,
              "currency": "EUR",
              "compact": {
                "prefix": "€",
                "content": "100.00",
                "suffix": "K"
              }
            },
            "age": 18,
            "fee": {
              "value": 350000,
              "currency": "EUR",
              "compact": {
                "prefix": "€",
                "content": "350.00",
                "suffix": "K"
              }
            },
            "season": {
              "id": 2019,
              "display": "19/20",
              "cyclicalName": "2020",
              "nonCyclicalName": "19/20"
            }
          },
          "typeDetails": {
            "type": "STANDARD",
            "name": "",
            "feeDescription": ""
          },
          "relativeUrl": "/boubacar-traore/transfers/spieler/649020/transfer_id/2652849"
        }
      ],
      "pending": [
        {
          "id": "5807622",
          "transferSource": {
            "competitionId": "FR1",
            "countryId": 50,
            "clubId": "347",
            "coachId": "60968"
          },
          "transferDestination": {
            "competitionId": "GB1",
            "countryId": 189,
            "clubId": "543",
            "coachId": "49800"
          },
          "details": {
            "playerId": "649020",
            "date": "2026-06-30T00:00:00+02:00",
            "contractUntilDate": "2027-06-30T00:00:00+02:00",
            "seasonId": 2025,
            "isPending": true,
            "marketValue": {
              "value": 5000000,
              "currency": "EUR",
              "compact": {
                "prefix": "€",
                "content": "5.00",
                "suffix": "M"
              }
            },
            "age": 24,
            "remainingContractPeriod": {
              "days": 0,
              "daysDisplay": "Unknown"
            },
            "season": {
              "id": 2025,
              "display": "25/26",
              "cyclicalName": "2026",
              "nonCyclicalName": "25/26"
            }
          },
          "typeDetails": {
            "type": "RETURNED_FROM_PREVIOUS_LOAN",
            "name": "End of loan",
            "feeDescription": "End of loan"
          },
          "relativeUrl": "/boubacar-traore/transfers/spieler/649020/transfer_id/5807622"
        }
      ],
      "url": "",
      "feeSum": {
        "value": 13350000,
        "currency": "EUR",
        "compact": {
          "prefix": "€",
          "content": "13.35",
          "suffix": "M"
        }
      },
      "averageAge": 24,
      "totalMarketValue": {
        "value": 5000000,
        "currency": "EUR",
        "compact": {
          "prefix": "€",
          "content": "5.00",
          "suffix": "M"
        }
      }
    },
    "clubIds": [
      "347",
      "543",
      "21375"
    ],
    "coachIds": [
      "60968",
      "49800",
      "7571",
      "7218",
      "1227",
      "6615",
      "61477",
      "27454"
    ],
    "competitionIds": [
      "FR1",
      "GB1",
      "FR2"
    ],
    "mostRecentTransfer": {
      "id": "5807621",
      "transferSource": {
        "competitionId": "GB1",
        "countryId": 189,
        "clubId": "543",
        "coachId": "7571"
      },
      "transferDestination": {
        "competitionId": "FR1",
        "countryId": 50,
        "clubId": "347",
        "coachId": "7218"
      },
      "details": {
        "playerId": "649020",
        "date": "2025-07-24T00:00:00+02:00",
        "contractUntilDate": "2026-06-30T00:00:00+02:00",
        "seasonId": 2025,
        "isPending": false,
        "marketValue": {
          "value": 5000000,
          "currency": "EUR",
          "compact": {
            "prefix": "€",
            "content": "5.00",
            "suffix": "M"
          }
        },
        "age": 23,
        "remainingContractPeriod": {
          "days": 706,
          "daysDisplay": "1 Year, 11 Months, 6 Days"
        },
        "season": {
          "id": 2025,
          "display": "25/26",
          "cyclicalName": "2026",
          "nonCyclicalName": "25/26"
        }
      },
      "typeDetails": {
        "type": "ACTIVE_LOAN_TRANSFER",
        "name": "loan transfer",
        "feeDescription": "loan transfer"
      },
      "relativeUrl": "/boubacar-traore/transfers/spieler/649020/transfer_id/5807621"
    }
  }
}